runmero/__init__.py
runmero/cli/__init__.py
runmero/cli/main.py
runmero/core/__init__.py
runmero/core/manager.py
runmero/core/process.py
runmero/core/signal_handler.py
runmero/data/__init__.py
runmero/data/framework_templates.py
runmero/data/large_data.py
runmero/data/server_configs.py
runmero/frameworks/__init__.py
runmero/frameworks/django_server.py
runmero/frameworks/fastapi_server.py
runmero/frameworks/flask_server.py
runmero/frameworks/tornado_server.py
runmero/services/__init__.py
runmero/services/background.py
runmero/services/monitor.py
runmero/termux/__init__.py
runmero/termux/optimizer.py
runmero/termux/persistence.py
runmero/utils/__init__.py
runmero/utils/console.py
runmero/utils/installer.py
runmero-2.5.0.dist-info/METADATA
runmero-2.5.0.dist-info/WHEEL
runmero-2.5.0.dist-info/entry_points.txt
runmero-2.5.0.dist-info/top_level.txt
runmero-2.5.0.dist-info/RECORD
