Metadata-Version: 2.1
Name: runmero
Version: 2.5.0
Summary: مكتبة RunMero القوية لإدارة العمليات في الخلفية مع دعم أطر الويب المتعددة في بيئة Termux - 
Home-page: https://github.com/mero-palestine/runmero
Author: mero
Author-email: mero <mero@palestine.ps>
Maintainer-email: mero <mero@palestine.ps>
License: MIT
Project-URL: Homepage, https://github.com/mero-palestine/runmero
Project-URL: Documentation, https://runmero.readthedocs.io
Project-URL: Repository, https://github.com/mero-palestine/runmero.git
Project-URL: Bug Tracker, https://github.com/mero-palestine/runmero/issues
Project-URL: Source Code, https://github.com/mero-palestine/runmero
Keywords: termux,background-processes,web-servers,process-management,fastapi,flask,django,tornado,android,mobile-development,palestine
Platform: linux
Platform: android
Classifier: Development Status :: 5 - Production/Stable
Classifier: Intended Audience :: Developers
Classifier: License :: OSI Approved :: MIT License
Classifier: Operating System :: Android
Classifier: Operating System :: POSIX :: Linux
Classifier: Programming Language :: Python :: 3
Classifier: Programming Language :: Python :: 3.11
Classifier: Programming Language :: Python :: 3.12
Classifier: Topic :: Software Development :: Libraries :: Python Modules
Classifier: Topic :: System :: Systems Administration
Classifier: Topic :: Internet :: WWW/HTTP :: WSGI :: Server
Classifier: Topic :: Internet :: WWW/HTTP :: HTTP Servers
Classifier: Environment :: Console
Classifier: Framework :: AsyncIO
Classifier: Framework :: Django
Classifier: Framework :: FastAPI
Classifier: Framework :: Flask
Requires-Python: >=3.8
Requires-Dist: celery>=5.3.0
Requires-Dist: click>=8.1.0
Requires-Dist: cryptography>=41.0.0
Requires-Dist: django>=4.2.0
Requires-Dist: fastapi>=0.104.0
Requires-Dist: flask-cors>=4.0.0
Requires-Dist: flask>=3.0.0
Requires-Dist: gunicorn>=21.2.0
Requires-Dist: psutil>=5.9.0
Requires-Dist: pydantic>=2.5.0
Requires-Dist: redis>=5.0.0
Requires-Dist: requests>=2.31.0
Requires-Dist: rich>=13.7.0
Requires-Dist: setuptools>=80.9.0
Requires-Dist: tornado>=6.4.0
Requires-Dist: uvicorn[standard]>=0.24.0
Requires-Dist: watchdog>=3.0.0
Requires-Dist: websockets>=12.0
Requires-Dist: aiofiles>=23.2.0
Provides-Extra: dev
Requires-Dist: pytest>=7.4.0; extra == "dev"
Requires-Dist: pytest-asyncio>=0.21.0; extra == "dev"
Requires-Dist: pytest-cov>=4.1.0; extra == "dev"
Requires-Dist: black>=23.7.0; extra == "dev"
Requires-Dist: flake8>=6.0.0; extra == "dev"
Requires-Dist: mypy>=1.5.0; extra == "dev"
Requires-Dist: pre-commit>=3.3.0; extra == "dev"
Provides-Extra: docs
Requires-Dist: sphinx>=7.1.0; extra == "docs"
Requires-Dist: sphinx-rtd-theme>=1.3.0; extra == "docs"
Requires-Dist: sphinx-autodoc-typehints>=1.24.0; extra == "docs"
Provides-Extra: testing
Requires-Dist: pytest>=7.4.0; extra == "testing"
Requires-Dist: pytest-asyncio>=0.21.0; extra == "testing"
Requires-Dist: pytest-cov>=4.1.0; extra == "testing"
Requires-Dist: httpx>=0.24.0; extra == "testing"
Requires-Dist: pytest-mock>=3.11.0; extra == "testing"
